efatfs/__init__.py
efatfs/diskio.py
efatfs/version.py
efatfs/wrapper.cpython-310-darwin.so
efatfs-0.0.9.dist-info/LICENSE.md
efatfs-0.0.9.dist-info/METADATA
efatfs-0.0.9.dist-info/WHEEL
efatfs-0.0.9.dist-info/top_level.txt
efatfs-0.0.9.dist-info/RECORD
